pilothub/__init__.py
pilothub/ppt2hb.py
pilothub/pptnotes.py
pilothub/pptx2content.py
pilothub/withopenai.py
pilothub-0.1.8.2.dist-info/LICENSE
pilothub-0.1.8.2.dist-info/METADATA
pilothub-0.1.8.2.dist-info/WHEEL
pilothub-0.1.8.2.dist-info/top_level.txt
pilothub-0.1.8.2.dist-info/RECORD
