Metadata-Version: 2.1
Name: pilothub
Version: 0.1.8.2
Summary: A short description of your project
Home-page: https://github.com/Bluedata-Consulting/pilothub
Author: Blue Data Consulting
Author-email: anshu@bluedataconsulting.com
License-File: LICENSE
Requires-Dist: openai ==1.14.3
Requires-Dist: python-pptx ==0.6.23
Requires-Dist: python-docx ==1.1.0
Requires-Dist: comtypes ==1.2.0
